ytbtimecodes/timecodes.py
ytbtimecodes-0.11.dist-info/METADATA
ytbtimecodes-0.11.dist-info/WHEEL
ytbtimecodes-0.11.dist-info/RECORD
